pyfmodex/__init__.py
pyfmodex/callback_prototypes.py
pyfmodex/channel.py
pyfmodex/channel_control.py
pyfmodex/channel_group.py
pyfmodex/cone_settings.py
pyfmodex/constants.py
pyfmodex/dsp.py
pyfmodex/dsp_connection.py
pyfmodex/enums.py
pyfmodex/exceptions.py
pyfmodex/flags.py
pyfmodex/fmodex.py
pyfmodex/fmodobject.py
pyfmodex/function_prototypes.py
pyfmodex/geometry.py
pyfmodex/globalvars.py
pyfmodex/reverb.py
pyfmodex/reverb_presets.py
pyfmodex/roomproperties.py
pyfmodex/sound.py
pyfmodex/sound_group.py
pyfmodex/structobject.py
pyfmodex/structure_declarations.py
pyfmodex/structures.py
pyfmodex/studio/__init__.py
pyfmodex/studio/bank.py
pyfmodex/studio/enums.py
pyfmodex/studio/event_description.py
pyfmodex/studio/event_instance.py
pyfmodex/studio/flags.py
pyfmodex/studio/library.py
pyfmodex/studio/structures.py
pyfmodex/studio/studio_object.py
pyfmodex/studio/system.py
pyfmodex/studio/utils.py
pyfmodex/system.py
pyfmodex/utils.py
pyfmodex-0.7.1.dist-info/LICENSE
pyfmodex-0.7.1.dist-info/METADATA
pyfmodex-0.7.1.dist-info/WHEEL
pyfmodex-0.7.1.dist-info/RECORD
